{"cells":[{"dim":4096,"dtype":"int8","fraction_of_peak":0.24173749435964512,"iters":50,"peak_tflops":660.0,"per_iter_ms":0.8614337595645338,"telemetry":{"clock_mhz_max":2520.0,"clock_mhz_median":2520.0,"power_w_max":19.989,"power_w_mean":19.989,"sample_count":7,"sm_util_max":3.0,"sm_util_mean":3.0,"sm_util_median":3.0,"temp_c_max":34.0},"tflops_observed":159.54674627736577,"wall_time_ms":43.07168797822669},{"dim":8192,"dtype":"int8","fraction_of_peak":0.25013310167973535,"iters":50,"peak_tflops":660.0,"per_iter_ms":6.660160920582712,"telemetry":{"clock_mhz_max":2520.0,"clock_mhz_median":2520.0,"power_w_max":19.989,"power_w_mean":19.989000000000015,"sample_count":66,"sm_util_max":3.0,"sm_util_mean":3.0,"sm_util_median":3.0,"temp_c_max":34.0},"tflops_observed":165.0878471086253,"wall_time_ms":333.0080460291356},{"dim":4096,"dtype":"bf16","fraction_of_peak":0.9622453914528694,"iters":50,"peak_tflops":165.0,"per_iter_ms":0.8656454598531127,"telemetry":{"clock_mhz_max":2685.0,"clock_mhz_median":2520.0,"power_w_max":130.335,"power_w_mean":44.51033333333334,"sample_count":9,"sm_util_max":3.0,"sm_util_mean":3.0,"sm_util_median":3.0,"temp_c_max":41.0},"tflops_observed":158.77048958972344,"wall_time_ms":43.282272992655635},{"dim":8192,"dtype":"bf16","fraction_of_peak":1.0260546972698843,"iters":50,"peak_tflops":165.0,"per_iter_ms":6.494494740618393,"telemetry":{"clock_mhz_max":2685.0,"clock_mhz_median":2685.0,"power_w_max":130.335,"power_w_mean":130.335,"sample_count":64,"sm_util_max":3.0,"sm_util_mean":3.0,"sm_util_median":3.0,"temp_c_max":41.0},"tflops_observed":169.2990250495309,"wall_time_ms":324.72473703091964},{"dim":4096,"dtype":"fp16","fraction_of_peak":0.5264959550993171,"iters":50,"peak_tflops":330.0,"per_iter_ms":0.7910444005392492,"telemetry":{"clock_mhz_max":2775.0,"clock_mhz_median":2775.0,"power_w_max":360.861,"power_w_mean":360.86099999999993,"sample_count":8,"sm_util_max":39.0,"sm_util_mean":39.0,"sm_util_median":39.0,"temp_c_max":43.0},"tflops_observed":173.74366518277466,"wall_time_ms":39.55222002696246},{"dim":8192,"dtype":"fp16","fraction_of_peak":0.5027822673629634,"iters":50,"peak_tflops":330.0,"per_iter_ms":6.626831600442529,"telemetry":{"clock_mhz_max":2775.0,"clock_mhz_median":2775.0,"power_w_max":360.861,"power_w_mean":360.86100000000044,"sample_count":66,"sm_util_max":39.0,"sm_util_mean":39.0,"sm_util_median":39.0,"temp_c_max":43.0},"tflops_observed":165.91814822977793,"wall_time_ms":331.34158002212644},{"dim":4096,"dtype":"fp32","fraction_of_peak":0.6823669972761591,"iters":50,"peak_tflops":82.6,"per_iter_ms":2.438438340323046,"telemetry":{"clock_mhz_max":2760.0,"clock_mhz_median":2760.0,"power_w_max":361.452,"power_w_mean":361.45200000000006,"sample_count":24,"sm_util_max":39.0,"sm_util_mean":39.0,"sm_util_median":39.0,"temp_c_max":46.0},"tflops_observed":56.36351397501074,"wall_time_ms":121.92191701615229},{"dim":8192,"dtype":"fp32","fraction_of_peak":0.6944442536099764,"iters":50,"peak_tflops":82.6,"per_iter_ms":19.16824672021903,"telemetry":{"clock_mhz_max":2760.0,"clock_mhz_median":2370.0,"power_w_max":447.455,"power_w_mean":393.9123809523818,"sample_count":189,"sm_util_max":100.0,"sm_util_mean":82.57142857142857,"sm_util_median":100.0,"temp_c_max":58.0},"tflops_observed":57.361095348184044,"wall_time_ms":958.4123360109515}],"compute_capability":"8.9","device_name":"NVIDIA GeForce RTX 4090","generated_at":"2026-04-29T10:06:13Z","saturation_probe_version":"v1","torch_version":"2.5.1+cu124"}
